fastapi_oauth2/__init__.py
fastapi_oauth2/claims.py
fastapi_oauth2/client.py
fastapi_oauth2/config.py
fastapi_oauth2/core.py
fastapi_oauth2/exceptions.py
fastapi_oauth2/middleware.py
fastapi_oauth2/router.py
fastapi_oauth2/security.py
fastapi_oauth2-1.3.0.dist-info/LICENSE
fastapi_oauth2-1.3.0.dist-info/METADATA
fastapi_oauth2-1.3.0.dist-info/WHEEL
fastapi_oauth2-1.3.0.dist-info/top_level.txt
fastapi_oauth2-1.3.0.dist-info/RECORD
