Metadata-Version: 2.1
Name: fastapi-oauth2
Version: 1.3.0
Summary: Easy to integrate OAuth2 authentication with support for several identity providers.
Author: Artyom Vancyan
Author-email: artyom@pysnippet.org
License: MIT
Project-URL: Documentation, https://docs.pysnippet.org/fastapi-oauth2/
Project-URL: Source Code, https://github.com/pysnippet/fastapi-oauth2/
Keywords: python,sso,auth,login,oauth,oauth2,social,fastapi,allauth,security,middleware,authentication
Platform: unix
Platform: linux
Platform: osx
Platform: win32
Classifier: Operating System :: OS Independent
Classifier: Development Status :: 5 - Production/Stable
Classifier: Framework :: FastAPI
Classifier: Programming Language :: Python
Classifier: Programming Language :: Python :: 3
Classifier: Programming Language :: Python :: 3.7
Classifier: Programming Language :: Python :: 3.8
Classifier: Programming Language :: Python :: 3.9
Classifier: Programming Language :: Python :: 3.10
Classifier: Programming Language :: Python :: 3.11
Classifier: License :: OSI Approved :: MIT License
Requires-Python: >=3.7
License-File: LICENSE
Requires-Dist: fastapi>=0.68.1
Requires-Dist: httpx>=0.23.0
Requires-Dist: oauthlib>=3.2.2
Requires-Dist: python-jose>=3.3.0
Requires-Dist: social-auth-core>=4.4.2
Requires-Dist: starlette>=0.19.1
